jupyter_devcontainers/__init__.py
jupyter_devcontainers/__main__.py
jupyter_devcontainers/_version.py
jupyter_devcontainers/application.py
jupyter_devcontainers/serverapplication.py
jupyter_devcontainers/handlers/__init__.py
jupyter_devcontainers/handlers/base.py
jupyter_devcontainers/handlers/config/__init__.py
jupyter_devcontainers/handlers/config/handler.py
jupyter_devcontainers/handlers/devcontainers/__init__.py
jupyter_devcontainers/handlers/devcontainers/handler.py
jupyter_devcontainers/handlers/echo/__init__.py
jupyter_devcontainers/handlers/echo/handler.py
jupyter_devcontainers/handlers/index/__init__.py
jupyter_devcontainers/handlers/index/handler.py
jupyter_devcontainers/handlers/ping/__init__.py
jupyter_devcontainers/handlers/ping/handler.py
jupyter_devcontainers/handlers/proxy/__init__.py
jupyter_devcontainers/handlers/proxy/handler.py
jupyter_devcontainers/handlers/relay/__init__.py
jupyter_devcontainers/handlers/relay/handler.py
jupyter_devcontainers/static/102.jupyter-devcontainers.js
jupyter_devcontainers/static/1020.jupyter-devcontainers.js
jupyter_devcontainers/static/1050.jupyter-devcontainers.js
jupyter_devcontainers/static/1110.jupyter-devcontainers.js
jupyter_devcontainers/static/1146.jupyter-devcontainers.js
jupyter_devcontainers/static/1292.jupyter-devcontainers.js
jupyter_devcontainers/static/1450.jupyter-devcontainers.js
jupyter_devcontainers/static/1626.jupyter-devcontainers.js
jupyter_devcontainers/static/1629.jupyter-devcontainers.js
jupyter_devcontainers/static/1696.jupyter-devcontainers.js
jupyter_devcontainers/static/1810.jupyter-devcontainers.js
jupyter_devcontainers/static/1900.jupyter-devcontainers.js
jupyter_devcontainers/static/1919.jupyter-devcontainers.js
jupyter_devcontainers/static/1956.jupyter-devcontainers.js
jupyter_devcontainers/static/2.jupyter-devcontainers.js
jupyter_devcontainers/static/2003.jupyter-devcontainers.js
jupyter_devcontainers/static/2030.jupyter-devcontainers.js
jupyter_devcontainers-0.0.4.dist-info/METADATA
jupyter_devcontainers-0.0.4.dist-info/WHEEL
jupyter_devcontainers-0.0.4.dist-info/entry_points.txt
jupyter_devcontainers-0.0.4.dist-info/licenses/LICENSE
jupyter_devcontainers-0.0.4.dist-info/RECORD
